gcgen/__init__.py
gcgen/__main__.py
gcgen/decorators.py
gcgen/emitter.py
gcgen/excbase.py
gcgen/generate.py
gcgen/log.py
gcgen/scope.py
gcgen/snippetparser.py
gcgen/api/__init__.py
gcgen/api/snippets_helpers.py
gcgen/api/tree.py
gcgen/api/types.py
gcgen/api/write_file.py
gcgen-0.0.7.dist-info/METADATA
gcgen-0.0.7.dist-info/WHEEL
gcgen-0.0.7.dist-info/entry_points.txt
gcgen-0.0.7.dist-info/top_level.txt
gcgen-0.0.7.dist-info/RECORD
