Metadata-Version: 2.1
Name: gcgen
Version: 0.0.7
Summary: generate code in any language or format
Home-page: https://jwdevantier.github.io/gcgen/
Author: Jesper Wendel Devantier
Author-email: jwd@defmacro.it
License: MIT
Platform: UNKNOWN
Classifier: Framework :: Pytest
